axisregistry/__init__.py
axisregistry/_version.py
axisregistry/axes_pb2.py
axisregistry/data/ar_retinal_resolution.textproto
axisregistry/data/bleed.textproto
axisregistry/data/bounce.textproto
axisregistry/data/casual.textproto
axisregistry/data/cursive.textproto
axisregistry/data/edge_highlight.textproto
axisregistry/data/element_expansion.textproto
axisregistry/data/element_grid.textproto
axisregistry/data/element_shape.textproto
axisregistry/data/extrusion_depth.textproto
axisregistry/data/fill.textproto
axisregistry/data/flare.textproto
axisregistry/data/grade.textproto
axisregistry/data/hyper_expansion.textproto
axisregistry/data/informality.textproto
axisregistry/data/italic.textproto
axisregistry/data/monospace.textproto
axisregistry/data/morph.textproto
axisregistry/data/optical_size.textproto
axisregistry/data/roundness.textproto
axisregistry/data/scanlines.textproto
axisregistry/data/shadow_length.textproto
axisregistry/data/sharpness.textproto
axisregistry/data/size_paint_1.textproto
axisregistry/data/size_paint_2.textproto
axisregistry/data/slant.textproto
axisregistry/data/softness.textproto
axisregistry/data/spacing.textproto
axisregistry/data/volume.textproto
axisregistry/data/weight.textproto
axisregistry/data/width.textproto
axisregistry/data/wonky.textproto
axisregistry/data/x_element_alignment.textproto
axisregistry/data/x_opaque.textproto
axisregistry/data/x_position_paint_1.textproto
axisregistry/data/x_position_paint_2.textproto
axisregistry/data/x_rotation.textproto
axisregistry/data/x_transparent.textproto
axisregistry/data/x_transparent_figures.textproto
axisregistry/data/y_element_alignment.textproto
axisregistry/data/y_opaque.textproto
axisregistry/data/y_position_paint_1.textproto
axisregistry/data/y_position_paint_2.textproto
axisregistry/data/y_rotation.textproto
axisregistry/data/y_transparent_ascender.textproto
axisregistry/data/y_transparent_descender.textproto
axisregistry/data/y_transparent_figures.textproto
axisregistry-0.4.10.dist-info/AUTHORS.txt
axisregistry-0.4.10.dist-info/LICENSE.txt
axisregistry-0.4.10.dist-info/METADATA
axisregistry-0.4.10.dist-info/WHEEL
axisregistry-0.4.10.dist-info/top_level.txt
axisregistry-0.4.10.dist-info/RECORD
