Metadata-Version: 2.1
Name: axisregistry
Version: 0.4.10
Summary: A python API to access data from the Google Fonts variable fonts axis registry.
Home-page: https://github.com/googlefonts/axisregistry/
Author: Felipe Sanches
Author-email: juca@members.fsf.org
Classifier: Intended Audience :: Developers
Classifier: Topic :: Text Processing :: Fonts
Classifier: License :: OSI Approved :: Apache Software License
Classifier: Operating System :: OS Independent
Classifier: Programming Language :: Python :: 3
Requires-Python: >=3.7
License-File: LICENSE.txt
License-File: AUTHORS.txt
Requires-Dist: protobuf<4,>=3.19.4
Requires-Dist: fonttools
